{
    "type": "CPMCellField",
    "inherits_from": ["CellField"],
    "boundary_conditions": {},
    "contained_objects": ["Cell"],
    "attributes": {
        "temperature": {
            "type": "float",
            "default": 37.0,
            "description": "Temperature of the Cellular Potts model environment."
        },
        "adhesion_matrix": {
            "type": "list[list[float]]",
            "description": "Matrix defining adhesion energies between different cell types."
        }
    }
}